bankinfo/__init__.py
bankinfo/validator.py
bankinfo-1.0.3.dist-info/METADATA
bankinfo-1.0.3.dist-info/WHEEL
bankinfo-1.0.3.dist-info/entry_points.txt
bankinfo-1.0.3.dist-info/RECORD
